{
  "project_info": {
    "project_number": "588990004533",
    "firebase_url": "https://projecthrm-e0008.firebaseio.com",
    "project_id": "projecthrm-e0008",
    "storage_bucket": "projecthrm-e0008.appspot.com"
  },
  "client": [
    {
      "client_info": {
        "mobilesdk_app_id": "1:588990004533:android:11757086507e5685",
        "android_client_info": {
          "package_name": "com.example.allu.hrm_contractor"
        }
      },
      "oauth_client": [
        {
          "client_id": "588990004533-cfpahggp4e8bim5eth5vkkseibki1jqo.apps.googleusercontent.com",
          "client_type": 3
        }
      ],
      "api_key": [
        {
          "current_key": "AIzaSyCF1_oipUxgb8AGMDCcqFyVLVwdGAjsIiI"
        }
      ],
      "services": {
        "analytics_service": {
          "status": 1
        },
        "appinvite_service": {
          "status": 1,
          "other_platform_oauth_client": []
        },
        "ads_service": {
          "status": 2
        }
      }
    }
  ],
  "configuration_version": "1"
}